BonusProgramService/__init__.py
BonusProgramService/__main__.py
BonusProgramService/api.py
BonusProgramService/const.py
BonusProgramService/service.py
pih_bonus-0.13.dist-info/METADATA
pih_bonus-0.13.dist-info/WHEEL
pih_bonus-0.13.dist-info/entry_points.txt
pih_bonus-0.13.dist-info/top_level.txt
pih_bonus-0.13.dist-info/RECORD
