Metadata-Version: 2.1
Name: pih-bonus
Version: 0.13
Summary: PIH Bonus Program service package
Home-page: https://pacifichosp.com/
Author: Nikita Karachentsev
Author-email: it@pacifichosp.com
License: MIT
Requires-Dist: ipih
